soteria/__init__.py
soteria/py.typed
soteria/api/__init__.py
soteria/api/cache.py
soteria/api/client.py
soteria/api/errors.py
soteria/models/__init__.py
soteria/models/asset.py
soteria/models/object.py
soteria/models/post.py
soteria/models/user.py
soteria/types/__init__.py
soteria/types/errors.py
soteria/types/post.py
soteria/types/user.py
pyteria-0.1.0.dist-info/LICENSE
pyteria-0.1.0.dist-info/METADATA
pyteria-0.1.0.dist-info/WHEEL
pyteria-0.1.0.dist-info/top_level.txt
pyteria-0.1.0.dist-info/RECORD
