Metadata-Version: 2.1
Name: pyteria
Version: 0.1.0
Summary: A Python API library for Soteria, world's safest Twitter.
Author-email: Emma Terzioglu <emreterzioglu49@gmail.com>
License: MIT
Project-URL: Homepage, https://codeberg.org/soteria/pyteria
Project-URL: Repository, https://codeberg.org/soteria/pyteria
Project-URL: Bug Tracker, https://codeberg.org/soteria/pyteria/issues
Requires-Python: >3.9
License-File: LICENSE
Requires-Dist: aiohttp>=3.9.5
Requires-Dist: attrs>=24.2.0
Requires-Dist: typing-extensions>=4.12.2
